catalearn/__init__.py
catalearn/admin.py
catalearn/catalearn.py
catalearn/connector.py
catalearn/custom_exceptions.py
catalearn/runner.py
catalearn/saver.py
catalearn/settings.py
catalearn/test.py
catalearn/upgrade.py
catalearn/resources/gpu_modules.json
catalearn-1.1.7.dist-info/DESCRIPTION.rst
catalearn-1.1.7.dist-info/METADATA
catalearn-1.1.7.dist-info/RECORD
catalearn-1.1.7.dist-info/WHEEL
catalearn-1.1.7.dist-info/metadata.json
catalearn-1.1.7.dist-info/top_level.txt
