Metadata-Version: 2.0
Name: catalearn
Version: 1.1.7
Summary: A module for running machine learning code on cloud GPUs
Home-page: https://github.com/Catalearn/catalearn
Author: Edward Liu
Author-email: edward@catalearn.com
License: MIT
Keywords: machinelearning gpu cloud
Platform: any
Requires-Python: >=3
Requires-Dist: bs4
Requires-Dist: dill
Requires-Dist: requests
Requires-Dist: requests-toolbelt
Requires-Dist: tqdm
Requires-Dist: websocket-client
